setup.py
novalmber/__init__.py
novalmber/communication.py
novalmber.egg-info/PKG-INFO
novalmber.egg-info/SOURCES.txt
novalmber.egg-info/dependency_links.txt
novalmber.egg-info/top_level.txt