Metadata-Version: 1.0
Name: novalmber
Version: 0.2
Summary: A plugin interface and developer package for NovalIDE.
Home-page: https://gitee.com/hzy15610046011/TakagiABM
Author: Zhanyi Hou
Author-email: 3120388018@qq.com
License: MuLan2.0
Platform: UNKNOWN
